{
  "page_width": 2480,
  "page_height": 3508,
  "words": [
    "GROUP",
    "GENERAL",
    "MANAGER",
    "-",
    "DIRECT",
    "TO",
    "CONSUMER",
    "PPP",
    "HHH",
    "BID",
    "AMERICA",
    "PPP",
    "LTD",
    "16/03/2022",
    "-",
    "15/04/2022",
    "31",
    "13/04/2022",
    "Hours",
    "Rate",
    "/",
    "Perc",
    "Amount",
    "Normal",
    "Hours",
    "(Autopay)",
    "264.67",
    "Hrs",
    "289.7735",
    "31,350.00",
    "264.67",
    "31,350.00",
    "Additions",
    "CAR",
    "ALLOW",
    "2,183.33",
    "B",
    "Banking",
    "CBA",
    "20,208.33",
    "Smart",
    "This",
    "Pay",
    "Period",
    "to",
    "Date",
    "Year",
    "to",
    "Date",
    "pe",
    "SMART",
    "HERITAGE,",
    "SMART",
    "-",
    "FIX",
    "2,391.66",
    "2,391.66",
    "11,558.30",
    "Leave",
    "in",
    "Days",
    "as",
    "at",
    "31/03/2022",
    "Entitlement",
    "Prorata",
    "Taken",
    "Total",
    "Annual",
    "Leave",
    "6.58",
    "Taxable",
    "Income",
    "33,433.33",
    "166,766.65",
    "Smart",
    "2,391.66",
    "11,558.30",
    "Additions",
    "After",
    "Tax",
    "0.00",
    "0.00",
    "Annual",
    "Salary",
    "375,100.00",
    "Gross",
    "33,433.33",
    "166,766.65",
    "Tax",
    "-13,325.00",
    "-66,225.00",
    "Deductions",
    "After",
    "Tax",
    "0.00",
    "0.00",
    "NET",
    "PAY",
    "20,208.33",
    "100,641.65"
  ],
  "labels": [
    "O",
    "O",
    "O",
    "O",
    "O",
    "O",
    "O",
    "O",
    "O",
    "O",
    "O",
    "O",
    "O",
    "B-BEGIN_PAY_PERIOD",
    "O",
    "B-END_PAY_PERIOD",
    "O",
    "B-PAY_DATE",
    "O",
    "O",
    "O",
    "O",
    "O",
    "O",
    "O",
    "O",
    "O",
    "O",
    "O",
    "O",
    "O",
    "O",
    "O",
    "O",
    "O",
    "O",
    "O",
    "O",
    "O",
    "O",
    "O",
    "O",
    "O",
    "O",
    "O",
    "O",
    "O",
    "O",
    "O",
    "O",
    "O",
    "O",
    "O",
    "O",
    "O",
    "O",
    "O",
    "O",
    "O",
    "O",
    "O",
    "O",
    "O",
    "O",
    "O",
    "O",
    "O",
    "O",
    "O",
    "O",
    "O",
    "O",
    "O",
    "B-GROSS_TAXABLE_PER_PERIOD",
    "O",
    "O",
    "O",
    "O",
    "O",
    "O",
    "O",
    "O",
    "O",
    "O",
    "O",
    "O",
    "O",
    "B-GROSS_PAY_PER_PERIOD",
    "O",
    "O",
    "B-PAYG_TAX_PER_PERIOD",
    "O",
    "O",
    "O",
    "O",
    "B-POST_TAX_DEDUCTIONS_PER_PERIOD",
    "O",
    "O",
    "O",
    "B-NET_PAY_PER_PERIOD",
    "O"
  ],
  "actual_boxes": [
    [
      484.5,
      642.0,
      598.5,
      667.5
    ],
    [
      616.5,
      642.0,
      771.0,
      667.5
    ],
    [
      786.0,
      642.0,
      946.5,
      666.0
    ],
    [
      961.5,
      655.5,
      970.5,
      658.5
    ],
    [
      984.0,
      642.0,
      1102.5,
      666.0
    ],
    [
      1114.5,
      642.0,
      1156.5,
      666.0
    ],
    [
      1171.5,
      642.0,
      1359.0,
      667.5
    ],
    [
      486.0,
      687.0,
      546.0,
      711.0
    ],
    [
      564.0,
      685.5,
      724.5,
      711.0
    ],
    [
      742.5,
      685.5,
      874.5,
      711.0
    ],
    [
      889.5,
      685.5,
      1071.0,
      711.0
    ],
    [
      1086.0,
      687.0,
      1143.0,
      711.0
    ],
    [
      1159.5,
      687.0,
      1216.5,
      711.0
    ],
    [
      486.0,
      729.0,
      646.5,
      757.5
    ],
    [
      660.0,
      744.0,
      667.5,
      747.0
    ],
    [
      682.5,
      729.0,
      843.0,
      757.5
    ],
    [
      1188.0,
      729.0,
      1221.0,
      756.0
    ],
    [
      1822.5,
      729.0,
      1984.5,
      757.5
    ],
    [
      738.0,
      937.5,
      829.5,
      979.5
    ],
    [
      988.5,
      943.5,
      1057.5,
      969.0
    ],
    [
      1068.0,
      943.5,
      1078.5,
      970.5
    ],
    [
      1089.0,
      943.5,
      1155.0,
      969.0
    ],
    [
      1288.5,
      943.5,
      1417.5,
      967.5
    ],
    [
      211.5,
      1054.5,
      313.5,
      1080.0
    ],
    [
      328.5,
      1056.0,
      409.5,
      1080.0
    ],
    [
      424.5,
      1054.5,
      565.5,
      1086.0
    ],
    [
      729.0,
      1050.0,
      826.5,
      1092.0
    ],
    [
      910.5,
      1051.5,
      955.5,
      1092.0
    ],
    [
      1024.5,
      1050.0,
      1153.5,
      1092.0
    ],
    [
      1267.5,
      1054.5,
      1411.5,
      1083.0
    ],
    [
      730.5,
      1093.5,
      828.0,
      1137.0
    ],
    [
      1267.5,
      1099.5,
      1413.0,
      1129.5
    ],
    [
      208.5,
      1159.5,
      358.5,
      1185.0
    ],
    [
      226.5,
      1209.0,
      289.5,
      1234.5
    ],
    [
      303.0,
      1209.0,
      415.5,
      1233.0
    ],
    [
      1275.0,
      1209.0,
      1399.5,
      1237.5
    ],
    [
      1417.5,
      1209.0,
      1432.5,
      1233.0
    ],
    [
      211.5,
      1269.0,
      337.5,
      1300.5
    ],
    [
      226.5,
      1317.0,
      289.5,
      1342.5
    ],
    [
      1258.5,
      1317.0,
      1402.5,
      1347.0
    ],
    [
      210.0,
      1371.0,
      459.0,
      1413.0
    ],
    [
      1272.0,
      1377.0,
      1333.5,
      1404.0
    ],
    [
      1347.0,
      1378.5,
      1401.0,
      1410.0
    ],
    [
      1474.5,
      1377.0,
      1566.0,
      1404.0
    ],
    [
      1579.5,
      1380.0,
      1603.5,
      1402.5
    ],
    [
      1618.5,
      1378.5,
      1683.0,
      1404.0
    ],
    [
      1758.0,
      1378.5,
      1828.5,
      1404.0
    ],
    [
      1839.0,
      1380.0,
      1863.0,
      1404.0
    ],
    [
      1878.0,
      1378.5,
      1942.5,
      1404.0
    ],
    [
      223.5,
      1425.0,
      265.5,
      1488.0
    ],
    [
      444.0,
      1425.0,
      552.0,
      1450.5
    ],
    [
      568.5,
      1425.0,
      742.5,
      1453.5
    ],
    [
      757.5,
      1425.0,
      1060.5,
      1450.5
    ],
    [
      1053.0,
      1420.5,
      1080.0,
      1461.0
    ],
    [
      1077.0,
      1425.0,
      1144.5,
      1449.0
    ],
    [
      1275.0,
      1420.5,
      1399.5,
      1461.0
    ],
    [
      1558.5,
      1425.0,
      1683.0,
      1453.5
    ],
    [
      1801.5,
      1420.5,
      1942.5,
      1461.0
    ],
    [
      226.5,
      1521.0,
      316.5,
      1545.0
    ],
    [
      328.5,
      1519.5,
      355.5,
      1545.0
    ],
    [
      367.5,
      1521.0,
      442.5,
      1551.0
    ],
    [
      456.0,
      1525.5,
      490.5,
      1545.0
    ],
    [
      502.5,
      1521.0,
      532.5,
      1545.0
    ],
    [
      613.5,
      1519.5,
      775.5,
      1548.0
    ],
    [
      853.5,
      1566.0,
      1033.5,
      1591.5
    ],
    [
      1306.5,
      1567.5,
      1419.0,
      1591.5
    ],
    [
      1590.0,
      1566.0,
      1684.5,
      1593.0
    ],
    [
      1869.0,
      1566.0,
      1945.5,
      1593.0
    ],
    [
      229.5,
      1624.5,
      331.5,
      1650.0
    ],
    [
      346.5,
      1626.0,
      430.5,
      1650.0
    ],
    [
      1885.5,
      1624.5,
      1945.5,
      1650.0
    ],
    [
      223.5,
      2655.0,
      340.5,
      2680.5
    ],
    [
      354.0,
      2656.5,
      457.5,
      2682.0
    ],
    [
      592.5,
      2649.0,
      736.5,
      2691.0
    ],
    [
      985.5,
      2647.5,
      1146.0,
      2689.5
    ],
    [
      1240.5,
      2650.5,
      1471.5,
      2692.5
    ],
    [
      1629.0,
      2655.0,
      1753.5,
      2685.0
    ],
    [
      2038.5,
      2655.0,
      2179.5,
      2685.0
    ],
    [
      223.5,
      2712.0,
      357.0,
      2737.5
    ],
    [
      370.5,
      2712.0,
      441.0,
      2737.5
    ],
    [
      450.0,
      2712.0,
      504.0,
      2736.0
    ],
    [
      676.5,
      2709.0,
      736.5,
      2734.5
    ],
    [
      1086.0,
      2709.0,
      1144.5,
      2733.0
    ],
    [
      1239.0,
      2712.0,
      1339.5,
      2737.5
    ],
    [
      1354.5,
      2712.0,
      1446.0,
      2743.5
    ],
    [
      2017.5,
      2712.0,
      2179.5,
      2740.5
    ],
    [
      226.5,
      2764.5,
      307.5,
      2805.0
    ],
    [
      592.5,
      2764.5,
      736.5,
      2805.0
    ],
    [
      985.5,
      2769.0,
      1146.0,
      2797.5
    ],
    [
      223.5,
      2823.0,
      277.5,
      2847.0
    ],
    [
      580.5,
      2814.0,
      735.0,
      2856.0
    ],
    [
      990.0,
      2818.5,
      1146.0,
      2847.0
    ],
    [
      226.5,
      2877.0,
      387.0,
      2904.0
    ],
    [
      387.0,
      2872.5,
      471.0,
      2914.5
    ],
    [
      478.5,
      2878.5,
      534.0,
      2902.5
    ],
    [
      676.5,
      2874.0,
      735.0,
      2901.0
    ],
    [
      1086.0,
      2874.0,
      1146.0,
      2899.5
    ],
    [
      226.5,
      2952.0,
      289.5,
      2976.0
    ],
    [
      301.5,
      2952.0,
      366.0,
      2976.0
    ],
    [
      592.5,
      2946.0,
      738.0,
      2988.0
    ],
    [
      985.5,
      2950.5,
      1147.5,
      2980.5
    ]
  ],
  "boxes": [
    [
      195,
      182,
      241,
      190
    ],
    [
      248,
      182,
      310,
      190
    ],
    [
      316,
      182,
      381,
      189
    ],
    [
      387,
      186,
      391,
      187
    ],
    [
      396,
      182,
      444,
      189
    ],
    [
      449,
      182,
      466,
      189
    ],
    [
      472,
      182,
      548,
      190
    ],
    [
      196,
      195,
      220,
      202
    ],
    [
      227,
      195,
      292,
      202
    ],
    [
      299,
      195,
      352,
      202
    ],
    [
      358,
      195,
      431,
      202
    ],
    [
      437,
      195,
      460,
      202
    ],
    [
      467,
      195,
      490,
      202
    ],
    [
      196,
      207,
      260,
      215
    ],
    [
      266,
      212,
      269,
      212
    ],
    [
      275,
      207,
      339,
      215
    ],
    [
      479,
      207,
      492,
      215
    ],
    [
      735,
      207,
      800,
      215
    ],
    [
      297,
      267,
      334,
      279
    ],
    [
      398,
      268,
      426,
      276
    ],
    [
      430,
      268,
      434,
      276
    ],
    [
      439,
      268,
      465,
      276
    ],
    [
      519,
      268,
      571,
      275
    ],
    [
      85,
      300,
      126,
      307
    ],
    [
      132,
      300,
      165,
      307
    ],
    [
      171,
      300,
      228,
      309
    ],
    [
      294,
      299,
      333,
      311
    ],
    [
      367,
      299,
      385,
      311
    ],
    [
      413,
      299,
      465,
      311
    ],
    [
      511,
      300,
      569,
      308
    ],
    [
      294,
      311,
      333,
      324
    ],
    [
      511,
      313,
      569,
      321
    ],
    [
      84,
      330,
      144,
      337
    ],
    [
      91,
      344,
      116,
      351
    ],
    [
      122,
      344,
      167,
      351
    ],
    [
      514,
      344,
      564,
      352
    ],
    [
      571,
      344,
      577,
      351
    ],
    [
      85,
      361,
      136,
      370
    ],
    [
      91,
      375,
      116,
      382
    ],
    [
      507,
      375,
      565,
      383
    ],
    [
      84,
      390,
      185,
      402
    ],
    [
      513,
      392,
      537,
      400
    ],
    [
      543,
      392,
      565,
      401
    ],
    [
      594,
      392,
      631,
      400
    ],
    [
      637,
      393,
      646,
      399
    ],
    [
      652,
      392,
      678,
      400
    ],
    [
      709,
      392,
      737,
      400
    ],
    [
      741,
      393,
      751,
      400
    ],
    [
      757,
      392,
      783,
      400
    ],
    [
      90,
      406,
      107,
      424
    ],
    [
      179,
      406,
      222,
      413
    ],
    [
      229,
      406,
      299,
      414
    ],
    [
      305,
      406,
      427,
      413
    ],
    [
      424,
      404,
      435,
      416
    ],
    [
      434,
      406,
      461,
      412
    ],
    [
      514,
      404,
      564,
      416
    ],
    [
      628,
      406,
      678,
      414
    ],
    [
      726,
      404,
      783,
      416
    ],
    [
      91,
      433,
      127,
      440
    ],
    [
      132,
      433,
      143,
      440
    ],
    [
      148,
      433,
      178,
      442
    ],
    [
      183,
      434,
      197,
      440
    ],
    [
      202,
      433,
      214,
      440
    ],
    [
      247,
      433,
      312,
      441
    ],
    [
      344,
      446,
      416,
      453
    ],
    [
      526,
      446,
      572,
      453
    ],
    [
      641,
      446,
      679,
      454
    ],
    [
      753,
      446,
      784,
      454
    ],
    [
      92,
      463,
      133,
      470
    ],
    [
      139,
      463,
      173,
      470
    ],
    [
      760,
      463,
      784,
      470
    ],
    [
      90,
      756,
      137,
      764
    ],
    [
      142,
      757,
      184,
      764
    ],
    [
      238,
      755,
      297,
      766
    ],
    [
      397,
      754,
      462,
      766
    ],
    [
      500,
      755,
      593,
      767
    ],
    [
      656,
      756,
      707,
      765
    ],
    [
      822,
      756,
      879,
      765
    ],
    [
      90,
      772,
      143,
      780
    ],
    [
      149,
      772,
      177,
      780
    ],
    [
      181,
      772,
      203,
      779
    ],
    [
      272,
      772,
      297,
      779
    ],
    [
      437,
      772,
      461,
      778
    ],
    [
      499,
      772,
      540,
      780
    ],
    [
      546,
      772,
      583,
      781
    ],
    [
      813,
      772,
      879,
      781
    ],
    [
      91,
      787,
      124,
      799
    ],
    [
      238,
      787,
      297,
      799
    ],
    [
      397,
      789,
      462,
      797
    ],
    [
      90,
      804,
      111,
      811
    ],
    [
      234,
      802,
      296,
      814
    ],
    [
      399,
      803,
      462,
      811
    ],
    [
      91,
      820,
      156,
      827
    ],
    [
      156,
      818,
      189,
      830
    ],
    [
      192,
      820,
      215,
      827
    ],
    [
      272,
      819,
      296,
      826
    ],
    [
      437,
      819,
      462,
      826
    ],
    [
      91,
      841,
      116,
      848
    ],
    [
      121,
      841,
      147,
      848
    ],
    [
      238,
      839,
      297,
      851
    ],
    [
      397,
      840,
      462,
      849
    ]
  ],
  "docid": "Customer_66_0_",
  "page": "0"
}